class test.TestCompact
    Minor version: 0
    Major version: 61
    Flags: PUBLIC, ABSTRACT, SUPER

    public void <init>();
        Flags: PUBLIC
        Code:
               0: aload_0         /* this */
               1: invokespecial   java/lang/Object.<init>:()V
               4: return

    public void method1(boolean flag);
        Flags: PUBLIC
        Code:
               0: aload_0         /* this */
               1: ldc             "Test.method1 start"
               3: invokevirtual   test/TestCompact.log:(Ljava/lang/String;)V
               6: iload_1         /* flag */
               7: ifeq            19
              10: aload_0         /* this */
              11: ldc             "Test.method1 if"
              13: invokevirtual   test/TestCompact.log:(Ljava/lang/String;)V
              16: goto            25
              19: aload_0         /* this */
              20: ldc             "Test.method1 else"
              22: invokevirtual   test/TestCompact.log:(Ljava/lang/String;)V
              25: aload_0         /* this */
              26: ldc             "Test.method1 end"
              28: invokevirtual   test/TestCompact.log:(Ljava/lang/String;)V
              31: return
        StackMapTable: 00 02 13 05

    public void method2();
        Flags: PUBLIC
        Code:
               0: aload_0         /* this */
               1: ldc             "Test.method2 start"
               3: invokevirtual   test/TestCompact.log:(Ljava/lang/String;)V
               6: aload_0         /* this */
               7: ldc             "Test.method2 try"
               9: invokevirtual   test/TestCompact.log:(Ljava/lang/String;)V
              12: aload_0         /* this */
              13: ldc             "Test.method2 finally"
              15: invokevirtual   test/TestCompact.log:(Ljava/lang/String;)V
              18: goto            46
              21: astore_1        /* e */
              22: aload_0         /* this */
              23: ldc             "Test.method2 catch"
              25: invokevirtual   test/TestCompact.log:(Ljava/lang/String;)V
              28: aload_0         /* this */
              29: ldc             "Test.method2 finally"
              31: invokevirtual   test/TestCompact.log:(Ljava/lang/String;)V
              34: goto            46
              37: astore_2
              38: aload_0         /* this */
              39: ldc             "Test.method2 finally"
              41: invokevirtual   test/TestCompact.log:(Ljava/lang/String;)V
              44: aload_2
              45: athrow
              46: aload_0         /* this */
              47: ldc             "Test.method2 end"
              49: invokevirtual   test/TestCompact.log:(Ljava/lang/String;)V
              52: return
        StackMapTable: 00 03 55 07 00 1B 4F 07 00 4F 08
        Exceptions:
            Try           Handler
            Start  End    Start  End    Type
            -----  -----  -----  -----  ---------------------
            6      12     21     37     Ljava/lang/Exception;
            6      12     37     46     Any
            21     28     37     46     Any

    public void method3(int[] arr);
        Flags: PUBLIC
        Code:
               0: aload_0         /* this */
               1: ldc             "Test.method3 start"
               3: invokevirtual   test/TestCompact.log:(Ljava/lang/String;)V
               6: iconst_0
               7: istore_2        /* i */
               8: iload_2         /* i */
               9: aload_1         /* arr */
              10: arraylength
              11: if_icmpge       26
              14: aload_0         /* this */
              15: ldc             "Test.method3 for"
              17: invokevirtual   test/TestCompact.log:(Ljava/lang/String;)V
              20: iinc            i, 1
              23: goto            8
              26: aload_0         /* this */
              27: ldc             "Test.method3 end"
              29: invokevirtual   test/TestCompact.log:(Ljava/lang/String;)V
              32: return
        StackMapTable: 00 02 FC 00 08 01 FA 00 11

    public void method4(int i);
        Flags: PUBLIC
        Code:
               0: aload_0         /* this */
               1: ldc             "Test.method4 start"
               3: invokevirtual   test/TestCompact.log:(Ljava/lang/String;)V
               6: iload_1         /* i */
               7: tableswitch {
                          0: 36
                          1: 45
                          2: 54
                          3: 63
                    default: 72
                  }
              36: aload_0         /* this */
              37: ldc             "Test.method4 case 0"
              39: invokevirtual   test/TestCompact.log:(Ljava/lang/String;)V
              42: goto            78
              45: aload_0         /* this */
              46: ldc             "Test.method4 case 1"
              48: invokevirtual   test/TestCompact.log:(Ljava/lang/String;)V
              51: goto            78
              54: aload_0         /* this */
              55: ldc             "Test.method4 case 2"
              57: invokevirtual   test/TestCompact.log:(Ljava/lang/String;)V
              60: goto            78
              63: aload_0         /* this */
              64: ldc             "Test.method4 case 3"
              66: invokevirtual   test/TestCompact.log:(Ljava/lang/String;)V
              69: goto            78
              72: aload_0         /* this */
              73: ldc             "Test.method4 default"
              75: invokevirtual   test/TestCompact.log:(Ljava/lang/String;)V
              78: aload_0         /* this */
              79: ldc             "Test.method4 end"
              81: invokevirtual   test/TestCompact.log:(Ljava/lang/String;)V
              84: return
        StackMapTable: 00 06 24 08 08 08 08 05

    public java.lang.String method5(int i);
        Flags: PUBLIC
        Code:
               0: aload_0         /* this */
               1: ldc             "Test.method5 start"
               3: invokevirtual   test/TestCompact.log:(Ljava/lang/String;)V
               6: iload_1         /* i */
               7: tableswitch {
                          0: 36
                          1: 41
                          2: 46
                          3: 51
                    default: 56
                  }
              36: ldc             "Test.method4 case 0"
              38: goto            64
              41: ldc             "Test.method4 case 1"
              43: goto            64
              46: ldc             "Test.method4 case 2"
              48: goto            64
              51: ldc             "Test.method4 case 3"
              53: goto            64
              56: new             Ljava/lang/IllegalArgumentException;
              59: dup
              60: invokespecial   java/lang/IllegalArgumentException.<init>:()V
              63: athrow
              64: astore_2        /* s */
              65: aload_2         /* s */
              66: invokedynamic   BootstrapMethod #0, makeConcatWithConstants:(Ljava/lang/String;)Ljava/lang/String;
              71: areturn
        StackMapTable: 00 06 24 04 04 04 04 47 07 00 5D

    public void method5();
        Flags: PUBLIC
        Code:
               0: aload_0         /* this */
               1: ldc             "Test.method5"
               3: invokevirtual   test/TestCompact.log:(Ljava/lang/String;)V
               6: return

    public void method6();
        Flags: PUBLIC
        Code:
               0: aload_0         /* this */
               1: ldc             "Test.method6"
               3: invokevirtual   test/TestCompact.log:(Ljava/lang/String;)V
               6: return

    public abstract void log(java.lang.String p0);
        Flags: PUBLIC, ABSTRACT

class test.TestCompact.Inner4
    Minor version: 0
    Major version: 61
    Flags: SUPER

    final test.TestCompact this$0;
        Flags: FINAL, SYNTHETIC

    public void <init>(test.TestCompact this$0);
        Flags: PUBLIC
        Code:
               0: aload_0         /* this */
               1: aload_1         /* this$0 */
               2: putfield        test/TestCompact$Inner4.this$0:Ltest/TestCompact;
               5: aload_0         /* this */
               6: invokespecial   java/lang/Object.<init>:()V
               9: aload_1         /* this$0 */
              10: ldc             "Inner4 constructor"
              12: invokevirtual   test/TestCompact.log:(Ljava/lang/String;)V
              15: return

    public void method1();
        Flags: PUBLIC
        Code:
               0: aload_0         /* this */
               1: getfield        test/TestCompact$Inner4.this$0:Ltest/TestCompact;
               4: ldc             "Inner4.method1"
               6: invokevirtual   test/TestCompact.log:(Ljava/lang/String;)V
               9: return

    public void method2();
        Flags: PUBLIC
        Code:
               0: aload_0         /* this */
               1: getfield        test/TestCompact$Inner4.this$0:Ltest/TestCompact;
               4: ldc             "Inner4.method2"
               6: invokevirtual   test/TestCompact.log:(Ljava/lang/String;)V
               9: return

    public boolean equals(java.lang.Object o);
        Flags: PUBLIC
        Code:
               0: new             Ljava/lang/UnsupportedOperationException;
               3: dup
               4: ldc             "equals"
               6: invokespecial   java/lang/UnsupportedOperationException.<init>:(Ljava/lang/String;)V
               9: athrow

    public int hashCode();
        Flags: PUBLIC
        Code:
               0: new             Ljava/lang/UnsupportedOperationException;
               3: dup
               4: ldc             "hashCode"
               6: invokespecial   java/lang/UnsupportedOperationException.<init>:(Ljava/lang/String;)V
               9: athrow

    public java.lang.String toString();
        Flags: PUBLIC
        Code:
               0: new             Ljava/lang/UnsupportedOperationException;
               3: dup
               4: ldc             "toString"
               6: invokespecial   java/lang/UnsupportedOperationException.<init>:(Ljava/lang/String;)V
               9: athrow

class test.TestCompact.Inner3
    Minor version: 0
    Major version: 61
    Flags: SUPER

    final test.TestCompact this$0;
        Flags: FINAL, SYNTHETIC

    public void <init>(test.TestCompact this$0);
        Flags: PUBLIC
        Code:
               0: aload_0         /* this */
               1: aload_1         /* this$0 */
               2: putfield        test/TestCompact$Inner3.this$0:Ltest/TestCompact;
               5: aload_0         /* this */
               6: invokespecial   java/lang/Object.<init>:()V
               9: aload_1         /* this$0 */
              10: ldc             "Inner3 constructor"
              12: invokevirtual   test/TestCompact.log:(Ljava/lang/String;)V
              15: return

    public void method1();
        Flags: PUBLIC
        Code:
               0: new             Ljava/lang/Thread;
               3: dup
               4: new             Ltest/TestCompact$Inner3$1;
               7: dup
               8: aload_0         /* this */
               9: invokespecial   test/TestCompact$Inner3$1.<init>:(Ltest/TestCompact$Inner3;)V
              12: invokespecial   java/lang/Thread.<init>:(Ljava/lang/Runnable;)V
              15: invokevirtual   java/lang/Thread.start:()V
              18: return

    public void method2();
        Flags: PUBLIC
        Code:
               0: new             Ljava/lang/Thread;
               3: dup
               4: aload_0         /* this */
               5: invokedynamic   BootstrapMethod #0, run:(Ltest/TestCompact$Inner3;)Ljava/lang/Runnable;
              10: invokespecial   java/lang/Thread.<init>:(Ljava/lang/Runnable;)V
              13: invokevirtual   java/lang/Thread.start:()V
              16: return

    public void method3();
        Flags: PUBLIC
        Code:
               0: new             Ljava/lang/Thread;
               3: dup
               4: aload_0         /* this */
               5: invokedynamic   BootstrapMethod #1, run:(Ltest/TestCompact$Inner3;)Ljava/lang/Runnable;
              10: invokespecial   java/lang/Thread.<init>:(Ljava/lang/Runnable;)V
              13: invokevirtual   java/lang/Thread.start:()V
              16: return

    private void lambda$method3$1();
        Flags: PRIVATE, SYNTHETIC
        Code:
               0: aload_0         /* this */
               1: getfield        test/TestCompact$Inner3.this$0:Ltest/TestCompact;
               4: ldc             "Inner3.method3"
               6: invokevirtual   test/TestCompact.log:(Ljava/lang/String;)V
               9: return

    private void lambda$method2$0();
        Flags: PRIVATE, SYNTHETIC
        Code:
               0: aload_0         /* this */
               1: getfield        test/TestCompact$Inner3.this$0:Ltest/TestCompact;
               4: ldc             "Inner3.method2a"
               6: invokevirtual   test/TestCompact.log:(Ljava/lang/String;)V
               9: aload_0         /* this */
              10: getfield        test/TestCompact$Inner3.this$0:Ltest/TestCompact;
              13: ldc             "Inner3.method2b"
              15: invokevirtual   test/TestCompact.log:(Ljava/lang/String;)V
              18: return

class test.TestCompact$Inner3$1test.TestCompact.Inner3.TestCompact$Inner3$1
    Minor version: 0
    Major version: 61
    Flags: SUPER

    final test.TestCompact.Inner3 this$1;
        Flags: FINAL, SYNTHETIC

    void <init>(test.TestCompact.Inner3 this$1);
        Flags: SYNTHETIC, ANONCONSTR
        Code:
               0: aload_0         /* this */
               1: aload_1         /* this$1 */
               2: putfield        test/TestCompact$Inner3$1.this$1:Ltest/TestCompact$Inner3;
               5: aload_0         /* this */
               6: invokespecial   java/lang/Object.<init>:()V
               9: return

    public void run();
        Flags: PUBLIC
        Code:
               0: aload_0         /* this */
               1: getfield        test/TestCompact$Inner3$1.this$1:Ltest/TestCompact$Inner3;
               4: getfield        test/TestCompact$Inner3.this$0:Ltest/TestCompact;
               7: ldc             "Inner3.method1"
               9: invokevirtual   test/TestCompact.log:(Ljava/lang/String;)V
              12: return

class test.TestCompact.Inner1
    Minor version: 0
    Major version: 61
    Flags: SUPER

    final test.TestCompact this$0;
        Flags: FINAL, SYNTHETIC

    public void <init>(test.TestCompact this$0);
        Flags: PUBLIC
        Code:
               0: aload_0         /* this */
               1: aload_1         /* this$0 */
               2: putfield        test/TestCompact$Inner1.this$0:Ltest/TestCompact;
               5: aload_0         /* this */
               6: invokespecial   java/lang/Object.<init>:()V
               9: aload_1         /* this$0 */
              10: ldc             "Inner1 constructor"
              12: invokevirtual   test/TestCompact.log:(Ljava/lang/String;)V
              15: return

    public void method1(boolean flag);
        Flags: PUBLIC
        Code:
               0: aload_0         /* this */
               1: getfield        test/TestCompact$Inner1.this$0:Ltest/TestCompact;
               4: ldc             "Inner1.method1 start"
               6: invokevirtual   test/TestCompact.log:(Ljava/lang/String;)V
               9: iload_1         /* flag */
              10: ifeq            25
              13: aload_0         /* this */
              14: getfield        test/TestCompact$Inner1.this$0:Ltest/TestCompact;
              17: ldc             "Inner1.method1 while"
              19: invokevirtual   test/TestCompact.log:(Ljava/lang/String;)V
              22: goto            9
              25: aload_0         /* this */
              26: getfield        test/TestCompact$Inner1.this$0:Ltest/TestCompact;
              29: ldc             "Inner1.method1 end"
              31: invokevirtual   test/TestCompact.log:(Ljava/lang/String;)V
              34: return
        StackMapTable: 00 02 09 0F

    public void method2(boolean flag);
        Flags: PUBLIC
        Code:
               0: aload_0         /* this */
               1: getfield        test/TestCompact$Inner1.this$0:Ltest/TestCompact;
               4: ldc             "Inner1.method2 start"
               6: invokevirtual   test/TestCompact.log:(Ljava/lang/String;)V
               9: aload_0         /* this */
              10: getfield        test/TestCompact$Inner1.this$0:Ltest/TestCompact;
              13: ldc             "Inner1.method2 do while"
              15: invokevirtual   test/TestCompact.log:(Ljava/lang/String;)V
              18: iload_1         /* flag */
              19: ifne            9
              22: aload_0         /* this */
              23: getfield        test/TestCompact$Inner1.this$0:Ltest/TestCompact;
              26: ldc             "Inner1.method2 end"
              28: invokevirtual   test/TestCompact.log:(Ljava/lang/String;)V
              31: return
        StackMapTable: 00 01 09
